py_ds/__init__.py
py_ds/datastructures/__init__.py
py_ds/datastructures/heaps.py
py_ds/datastructures/linked_lists/__init__.py
py_ds/datastructures/linked_lists/doubly_linked.py
py_ds/datastructures/linked_lists/singly_linked.py
py_ds/datastructures/queue.py
py_ds/datastructures/stack.py
py_ds/datastructures/trees/__init__.py
py_ds/datastructures/trees/avl.py
py_ds/datastructures/trees/base.py
py_ds/datastructures/trees/binary_search_tree.py
py_ds_academy-0.5.18.dist-info/WHEEL
py_ds_academy-0.5.18.dist-info/METADATA
py_ds_academy-0.5.18.dist-info/RECORD
