Metadata-Version: 2.3
Name: py-ds-academy
Version: 0.5.18
Summary: Data structures implemented from scratch for learning and experimentation.
Keywords: data-structures,algorithms,learning
Author: Eytan Ohana
License: MIT
Classifier: Programming Language :: Python
Classifier: Programming Language :: Python :: 3
Classifier: Programming Language :: Python :: 3 :: Only
Classifier: Programming Language :: Python :: 3.10
Classifier: Programming Language :: Python :: 3.11
Classifier: Programming Language :: Python :: 3.12
Classifier: Programming Language :: Python :: 3.13
Classifier: Programming Language :: Python :: 3.14
Classifier: Intended Audience :: Developers
Classifier: License :: OSI Approved :: MIT License
Classifier: Topic :: Software Development :: Libraries
Classifier: Topic :: Education
Requires-Python: >=3.10
Project-URL: Homepage, https://github.com/eytanohana/py-ds-academy
Project-URL: Issues, https://github.com/eytanohana/py-ds-academy/issues
Project-URL: Repository, https://github.com/eytanohana/py-ds-academy
